nnbench/__init__.py
nnbench/__main__.py
nnbench/cli.py
nnbench/compare.py
nnbench/config.py
nnbench/context.py
nnbench/core.py
nnbench/fixtures.py
nnbench/py.typed
nnbench/runner.py
nnbench/types.py
nnbench/util.py
nnbench/reporter/__init__.py
nnbench/reporter/console.py
nnbench/reporter/file.py
nnbench/reporter/mlflow.py
nnbench/reporter/sqlite.py
nnbench/reporter/util.py
nnbench-0.5.0.dist-info/licenses/LICENSE
nnbench-0.5.0.dist-info/METADATA
nnbench-0.5.0.dist-info/WHEEL
nnbench-0.5.0.dist-info/entry_points.txt
nnbench-0.5.0.dist-info/top_level.txt
nnbench-0.5.0.dist-info/RECORD
