Metadata-Version: 2.4
Name: nnbench
Version: 0.5.0
Summary: A small framework for benchmarking machine learning models.
Author-email: appliedAI Initiative <info+oss@appliedai.de>
Maintainer-email: Nicholas Junge <n.junge@appliedai-institute.de>, Max Mynter <m.mynter@appliedai-institute.de>, Adrian Rumpold <a.rumpold@appliedai-institute.de>
License: Apache-2.0
Project-URL: Homepage, https://github.com/aai-institute/nnbench
Project-URL: Repository, https://github.com/aai-institute/nnbench.git
Project-URL: Issues, https://github.com/aai-institute/nnbench/issues
Project-URL: Discussions, https://github.com/aai-institute/nnbench/discussions
Keywords: Benchmarking,Machine Learning
Classifier: Development Status :: 4 - Beta
Classifier: Intended Audience :: Developers
Classifier: Intended Audience :: Science/Research
Classifier: License :: OSI Approved :: Apache Software License
Classifier: Operating System :: OS Independent
Classifier: Programming Language :: Python :: 3
Classifier: Topic :: Scientific/Engineering
Classifier: Topic :: Scientific/Engineering :: Artificial Intelligence
Classifier: Topic :: Scientific/Engineering :: Information Analysis
Classifier: Topic :: Software Development :: Libraries :: Python Modules
Classifier: Topic :: System :: Benchmark
Classifier: Topic :: Utilities
Classifier: Typing :: Typed
Requires-Python: >=3.10
License-File: LICENSE
Requires-Dist: rich
Requires-Dist: tomli>=1.1.0; python_version < "3.11"
Requires-Dist: typing-extensions; python_version < "3.11"
Dynamic: license-file
